pixeltracker/.env.example
pixeltracker/__init__.py
pixeltracker/__main__.py
pixeltracker/app.py
pixeltracker/screen.py
pixeltracker/settings.py
pixeltracker/resources/bitcoin-background.png
pixeltracker/resources/ethereum-background.png
pixeltracker/resources/polkadot-background.png
pixeltracker/resources/retro-pixel-petty-5h.ttf
pixeltracker/resources/yt-background.png
pixeltracker/tiles/__init__.py
pixeltracker/tiles/crypto.py
pixeltracker/tiles/tile.py
pixeltracker/tiles/yt_viewers.py
pixelart_tracker-0.1.4.dist-info/METADATA
pixelart_tracker-0.1.4.dist-info/WHEEL
pixelart_tracker-0.1.4.dist-info/entry_points.txt
pixelart_tracker-0.1.4.dist-info/licenses/LICENSE
pixelart_tracker-0.1.4.dist-info/RECORD
