Metadata-Version: 2.3
Name: pixelart-tracker
Version: 0.1.4
Summary: Show YouTube subscribers and Crypto-currency tracking on an iDotMatrix 32x32 pixels screen
Project-URL: Homepage, https://andresmolins.dev
Project-URL: Source, https://github.com/nesitor/pixelart-tracker
Author-email: "Andres D. Molins" <amolinsdiaz@yahoo.es>
Maintainer-email: "Andres D. Molins" <amolinsdiaz@yahoo.es>
License: MIT License
License-File: LICENSE
Keywords: bluetooth,idotmatrix,nesitor,statistics,subscribers,youtube
Requires-Python: >=3.10
Requires-Dist: aiohttp~=3.9
Requires-Dist: argparse
Requires-Dist: asyncio
Requires-Dist: colorlog~=6.8
Requires-Dist: idotmatrix==0.0.4
Requires-Dist: pillow~=10.3
Requires-Dist: pydantic[dotenv]~=1.10.13
